bgrm/__main__.py
bgrm/bgrm.py
bgrm/cam.py
bgrm/settings.py
bgrm/vid_file.py
bgrm/virt_cam.py
bgrm-11.dist-info/LICENSE
bgrm-11.dist-info/WHEEL
bgrm-11.dist-info/METADATA
bgrm-11.dist-info/RECORD
