Metadata-Version: 2.1
Name: bgrm
Version: 11
Summary: Remove backgrounds from video feeds in your web cam applications.
Home-page: https://github.com/blueOkiris/bgrm
License: GPL-3.0-only
Keywords: bgrm,background,removal,teams,linux,mediapipe,opencv,bg,rm
Author: Dylan Turner
Author-email: dylan.turner@tutanota.com
Requires-Python: >=3.8,<4.0
Classifier: License :: OSI Approved :: GNU General Public License v3 (GPLv3)
Classifier: Programming Language :: Python :: 3
Classifier: Programming Language :: Python :: 3.8
Classifier: Programming Language :: Python :: 3.9
Classifier: Programming Language :: Python :: 3.10
Classifier: Programming Language :: Python :: 3.11
Requires-Dist: cvzone (==1.5.3)
Requires-Dist: mediapipe (==0.10.0)
Requires-Dist: opencv-python (==4.6.0.66)
Requires-Dist: protobuf (==3.20.2)
Requires-Dist: v4l2-python3 (==0.3.1)
Project-URL: Repository, https://github.com/blueOkiris/bgrm
